{
  "date": "2026-02-07",
  "projects": {
    "SingularityBrainAi": {
      "totalLinesAdded": 267,
      "totalLinesRemoved": 0,
      "totalActiveTime": 3,
      "files": {
        "/Users/michaelmckenzie/SingularityBrainAi/tests/gpu/gpu_supported_forces_parity_smoke.spec.ts": [
          {
            "timestamp": "2026-02-07T11:52:55.024Z",
            "fileName": "/Users/michaelmckenzie/SingularityBrainAi/tests/gpu/gpu_supported_forces_parity_smoke.spec.ts",
            "fileType": ".ts",
            "linesAdded": 82,
            "linesRemoved": 0,
            "projectName": "SingularityBrainAi",
            "content": {
              "added": [],
              "removed": []
            },
            "duration": 0,
            "language": "ts"
          },
          {
            "timestamp": "2026-02-07T11:52:55.673Z",
            "fileName": "/Users/michaelmckenzie/SingularityBrainAi/tests/gpu/gpu_supported_forces_parity_smoke.spec.ts",
            "fileType": ".ts",
            "linesAdded": 59,
            "linesRemoved": 0,
            "projectName": "SingularityBrainAi",
            "content": {
              "added": [],
              "removed": []
            },
            "duration": 1,
            "language": "ts"
          },
          {
            "timestamp": "2026-02-07T12:20:10.869Z",
            "fileName": "/Users/michaelmckenzie/SingularityBrainAi/tests/gpu/gpu_supported_forces_parity_smoke.spec.ts",
            "fileType": ".ts",
            "linesAdded": 21,
            "linesRemoved": 0,
            "projectName": "SingularityBrainAi",
            "content": {
              "added": [],
              "removed": []
            },
            "duration": 1,
            "language": "ts"
          }
        ],
        "/Users/michaelmckenzie/SingularityBrainAi/src/tests/ParityHarness.ts": [
          {
            "timestamp": "2026-02-07T12:19:49.834Z",
            "fileName": "/Users/michaelmckenzie/SingularityBrainAi/src/tests/ParityHarness.ts",
            "fileType": ".ts",
            "linesAdded": 7,
            "linesRemoved": 0,
            "projectName": "SingularityBrainAi",
            "content": {
              "added": [],
              "removed": []
            },
            "duration": 0,
            "language": "ts"
          },
          {
            "timestamp": "2026-02-07T12:19:52.087Z",
            "fileName": "/Users/michaelmckenzie/SingularityBrainAi/src/tests/ParityHarness.ts",
            "fileType": ".ts",
            "linesAdded": 53,
            "linesRemoved": 0,
            "projectName": "SingularityBrainAi",
            "content": {
              "added": [],
              "removed": []
            },
            "duration": 1,
            "language": "ts"
          },
          {
            "timestamp": "2026-02-07T12:28:53.279Z",
            "fileName": "/Users/michaelmckenzie/SingularityBrainAi/src/tests/ParityHarness.ts",
            "fileType": ".ts",
            "linesAdded": 45,
            "linesRemoved": 0,
            "projectName": "SingularityBrainAi",
            "content": {
              "added": [],
              "removed": []
            },
            "duration": 0,
            "language": "ts"
          }
        ]
      },
      "languageStats": {
        "ts": 1
      },
      "changeFrequency": {
        "3": 1
      },
      "topFiles": [
        "/Users/michaelmckenzie/SingularityBrainAi/tests/gpu/gpu_supported_forces_parity_smoke.spec.ts"
      ],
      "averageChangeSize": 70.5
    }
  },
  "totalActiveTime": 1,
  "totalProjects": 1,
  "totalFiles": 1,
  "mostActiveHours": [
    3
  ],
  "mostUsedLanguages": [
    "ts"
  ]
}